{
	"pages": [ //pages数组中第一项表示应用启动页，参考：https://uniapp.dcloud.io/collocation/pages
		{
			"path": "pages/meeting/freeMeeting",
			"style": {
				"navigationStyle": "custom",
				"enablePullDownRefresh": false,
				"navigationBarTitleText": "会议列表"
			}
		},
		{
			"path": "pages/meeting/meeting",
			"style": {
				"navigationStyle": "custom",
				"enablePullDownRefresh": false,
				"navigationBarTitleText": "会议列表"
			}
		},
		{
			"path": "pages/my/my",
			"style": {
				"navigationStyle": "custom",
				"enablePullDownRefresh": false,
				"navigationBarTitleText": "添加会议"
			}
		}
	    ,{
            "path" : "pages/info/info",
            "style" :                                                                                    
            {
				"navigationStyle": "custom",
				"enablePullDownRefresh": false,
                "navigationBarTitleText": "会议详情"
            }
            
        },
		{
		    "path" : "pages/index/index",
		    "style" :                                                                                    
		    {
				"navigationStyle": "custom",
				"enablePullDownRefresh": false,
		        "navigationBarTitleText": "搜索"
		    }
		    
		},{
            "path" : "pages/login/login",
            "style" :                                                                                    
            {
                "navigationBarTitleText": "登录",
                "navigationStyle": "custom",
                "app-plus": {
                	"titleNView": false,
                	"animationType": "slide-in-bottom"
                }
            }
            
        }
    ],
	"globalStyle": {
		"navigationBarTextStyle": "black",
		"navigationBarTitleText": "uni-app",
		"navigationBarBackgroundColor": "#F8F8F8",
		"backgroundColor": "#F8F8F8"
	},
	"tabBar": {
	    "color": "#cdcdcd",
	    "selectedColor": "#61c3e7",
	    "borderStyle": "black",
	    "backgroundColor": "#ffffff",
	    "list": [{
	        "pagePath": "pages/meeting/meeting",
	        "iconPath": "static/dhuiyi.png",
	        "selectedIconPath": "static/huiyi.png",
			"text": "会议"
	    }, 
		{
	        "pagePath": "pages/my/my",
	        "iconPath": "static/dmine.png",
	        "selectedIconPath": "static/mine.png",
	        "text": "管理"
	    }]
	},
	"uniIdRouter": {},
	"easycom": {
		"^u-(.*)": "uview-ui/components/u-$1/u-$1.vue"
	}
}
